tabulator_webuntis_ap/__init__.py
tabulator_webuntis_ap/main.py
tabulator_webuntis_ap-0.5.0.dist-info/entry_points.txt
tabulator_webuntis_ap-0.5.0.dist-info/WHEEL
tabulator_webuntis_ap-0.5.0.dist-info/METADATA
tabulator_webuntis_ap-0.5.0.dist-info/RECORD
