Metadata-Version: 2.1
Name: tabulator-webuntis-ap
Version: 0.5.0
Summary: 
Author: Vincent Nys
Author-email: vincent.nys@ap.be
Requires-Python: >=3.7,<4.0
Classifier: Programming Language :: Python :: 3
Classifier: Programming Language :: Python :: 3.10
Classifier: Programming Language :: Python :: 3.7
Classifier: Programming Language :: Python :: 3.8
Classifier: Programming Language :: Python :: 3.9
Requires-Dist: PyYAML (>=6.0,<7.0)
Requires-Dist: click (>=8.1.3,<9.0.0)
Requires-Dist: webuntis (>=0.1.12,<0.2.0)
